<archimate:ArchimateDiagramModel
    xmlns:xsi="http://www.w3.org/2001/XMLSchema-instance"
    xmlns:archimate="http://www.archimatetool.com/archimate"
    name="Porter's Five Forces"
    id="id-37988">
  <children
      xsi:type="archimate:DiagramModelArchimateObject"
      id="id-47843"
      font="1|Arial|10.0|0|COCOA|1|"
      fontColor="#000000"
      lineColor="#404040"
      textAlignment="1"
      fillColor="#ffffff">
    <bounds
        x="40"
        y="53"
        width="280"
        height="240"/>
    <children
        xsi:type="archimate:DiagramModelArchimateObject"
        id="id-38031"
        font="1|Arial|10.0|0|COCOA|1|"
        fontColor="#000000"
        lineColor="#000000"
        fillColor="#ccccff">
      <bounds
          x="77"
          y="80"
          width="127"
          height="80"/>
      <archimateElement
          xsi:type="archimate:Assessment"
          href="Assessment_id-47214.xml#id-47214"/>
    </children>
    <archimateElement
        xsi:type="archimate:Grouping"
        href="Grouping_id-47864.xml#id-47864"/>
  </children>
  <children
      xsi:type="archimate:DiagramModelArchimateObject"
      id="id-47847"
      font="1|Arial|10.0|0|COCOA|1|"
      fontColor="#000000"
      lineColor="#404040"
      textAlignment="1"
      fillColor="#ffffff">
    <bounds
        x="327"
        y="53"
        width="240"
        height="487"/>
    <children
        xsi:type="archimate:DiagramModelArchimateObject"
        id="id-38023"
        font="1|Arial|10.0|0|COCOA|1|"
        fontColor="#000000"
        lineColor="#000000"
        fillColor="#ccccff">
      <bounds
          x="56"
          y="194"
          width="127"
          height="80"/>
      <archimateElement
          xsi:type="archimate:Assessment"
          href="Assessment_id-47224.xml#id-47224"/>
    </children>
    <archimateElement
        xsi:type="archimate:Grouping"
        href="Grouping_id-47866.xml#id-47866"/>
  </children>
  <children
      xsi:type="archimate:DiagramModelArchimateObject"
      id="id-47851"
      font="1|Arial|10.0|0|COCOA|1|"
      fontColor="#000000"
      lineColor="#404040"
      textAlignment="1"
      fillColor="#ffffff">
    <bounds
        x="573"
        y="53"
        width="280"
        height="240"/>
    <children
        xsi:type="archimate:DiagramModelArchimateObject"
        id="id-37999"
        font="1|Arial|10.0|0|COCOA|1|"
        fontColor="#000000"
        lineColor="#000000"
        fillColor="#ccccff">
      <bounds
          x="20"
          y="47"
          width="127"
          height="80"/>
      <archimateElement
          xsi:type="archimate:Assessment"
          href="Assessment_id-47245.xml#id-47245"/>
    </children>
    <children
        xsi:type="archimate:DiagramModelArchimateObject"
        id="id-38007"
        font="1|Arial|10.0|0|COCOA|1|"
        fontColor="#000000"
        lineColor="#000000"
        fillColor="#ccccff">
      <bounds
          x="114"
          y="140"
          width="127"
          height="80"/>
      <archimateElement
          xsi:type="archimate:Assessment"
          href="Assessment_id-47244.xml#id-47244"/>
    </children>
    <archimateElement
        xsi:type="archimate:Grouping"
        href="Grouping_id-47865.xml#id-47865"/>
  </children>
  <children
      xsi:type="archimate:DiagramModelArchimateObject"
      id="id-47855"
      font="1|Arial|10.0|0|COCOA|1|"
      fontColor="#000000"
      lineColor="#404040"
      textAlignment="1"
      fillColor="#ffffff">
    <bounds
        x="40"
        y="300"
        width="280"
        height="240"/>
    <children
        xsi:type="archimate:DiagramModelArchimateObject"
        id="id-37991"
        font="1|Arial|10.0|0|COCOA|1|"
        fontColor="#000000"
        lineColor="#000000"
        fillColor="#ccccff">
      <bounds
          x="77"
          y="87"
          width="127"
          height="80"/>
      <archimateElement
          xsi:type="archimate:Assessment"
          href="Assessment_id-47229.xml#id-47229"/>
    </children>
    <archimateElement
        xsi:type="archimate:Grouping"
        href="Grouping_id-47863.xml#id-47863"/>
  </children>
  <children
      xsi:type="archimate:DiagramModelArchimateObject"
      id="id-47859"
      font="1|Arial|10.0|0|COCOA|1|"
      fontColor="#000000"
      lineColor="#404040"
      textAlignment="1"
      fillColor="#ffffff">
    <bounds
        x="573"
        y="300"
        width="280"
        height="240"/>
    <children
        xsi:type="archimate:DiagramModelArchimateObject"
        id="id-38015"
        font="1|Arial|10.0|0|COCOA|1|"
        fontColor="#000000"
        lineColor="#000000"
        fillColor="#ccccff">
      <bounds
          x="77"
          y="87"
          width="127"
          height="80"/>
      <archimateElement
          xsi:type="archimate:Assessment"
          href="Assessment_id-47218.xml#id-47218"/>
    </children>
    <archimateElement
        xsi:type="archimate:Grouping"
        href="Grouping_id-47862.xml#id-47862"/>
  </children>
</archimate:ArchimateDiagramModel>
