<archimate:ArchimateDiagramModel
    xmlns:xsi="http://www.w3.org/2001/XMLSchema-instance"
    xmlns:archimate="http://www.archimatetool.com/archimate"
    name="Driver &amp; Business Goals"
    id="id-43485">
  <children
      xsi:type="archimate:DiagramModelArchimateObject"
      id="id-43488"
      targetConnections="id-43629"
      font="1|Arial|10.0|0|COCOA|1|"
      fontColor="#000000"
      lineColor="#000000"
      fillColor="#ccccff">
    <bounds
        x="140"
        y="360"
        width="133"
        height="53"/>
    <archimateElement
        xsi:type="archimate:Goal"
        href="Goal_id-47252.xml#id-47252"/>
  </children>
  <children
      xsi:type="archimate:DiagramModelArchimateObject"
      id="id-43496"
      targetConnections="id-43664"
      font="1|Arial|10.0|0|COCOA|1|"
      fontColor="#000000"
      lineColor="#000000"
      fillColor="#ccccff">
    <sourceConnections
        xsi:type="archimate:DiagramModelArchimateConnection"
        id="id-43624"
        font="1|Arial|10.0|0|COCOA|1|"
        fontColor="#000000"
        lineColor="#000000"
        source="id-43496"
        target="id-43616">
      <archimateRelationship
          xsi:type="archimate:InfluenceRelationship"
          href="InfluenceRelationship_id-47327.xml#id-47327"/>
    </sourceConnections>
    <sourceConnections
        xsi:type="archimate:DiagramModelArchimateConnection"
        id="id-43629"
        font="1|Arial|10.0|0|COCOA|1|"
        fontColor="#000000"
        lineColor="#000000"
        source="id-43496"
        target="id-43488">
      <archimateRelationship
          xsi:type="archimate:AggregationRelationship"
          href="AggregationRelationship_id-47339.xml#id-47339"/>
    </sourceConnections>
    <sourceConnections
        xsi:type="archimate:DiagramModelArchimateConnection"
        id="id-43634"
        font="1|Arial|10.0|0|COCOA|1|"
        fontColor="#000000"
        lineColor="#000000"
        source="id-43496"
        target="id-43504">
      <archimateRelationship
          xsi:type="archimate:AggregationRelationship"
          href="AggregationRelationship_id-47337.xml#id-47337"/>
    </sourceConnections>
    <bounds
        x="213"
        y="253"
        width="133"
        height="53"/>
    <archimateElement
        xsi:type="archimate:Goal"
        href="Goal_id-47257.xml#id-47257"/>
  </children>
  <children
      xsi:type="archimate:DiagramModelArchimateObject"
      id="id-43504"
      targetConnections="id-43634 id-43699"
      font="1|Arial|10.0|0|COCOA|1|"
      fontColor="#000000"
      lineColor="#000000"
      fillColor="#ccccff">
    <bounds
        x="300"
        y="360"
        width="127"
        height="53"/>
    <archimateElement
        xsi:type="archimate:Goal"
        href="Goal_id-47249.xml#id-47249"/>
  </children>
  <children
      xsi:type="archimate:DiagramModelArchimateObject"
      id="id-43512"
      targetConnections="id-43644 id-43679"
      font="1|Arial|10.0|0|COCOA|1|"
      fontColor="#000000"
      lineColor="#000000"
      fillColor="#ccccff">
    <sourceConnections
        xsi:type="archimate:DiagramModelArchimateConnection"
        id="id-43639"
        font="1|Arial|10.0|0|COCOA|1|"
        fontColor="#000000"
        lineColor="#000000"
        source="id-43512"
        target="id-43616">
      <archimateRelationship
          xsi:type="archimate:InfluenceRelationship"
          href="InfluenceRelationship_id-47330.xml#id-47330"/>
    </sourceConnections>
    <bounds
        x="507"
        y="253"
        width="153"
        height="53"/>
    <archimateElement
        xsi:type="archimate:Goal"
        href="Goal_id-47247.xml#id-47247"/>
  </children>
  <children
      xsi:type="archimate:DiagramModelArchimateObject"
      id="id-43520"
      targetConnections="id-43669 id-43674"
      font="1|Arial|10.0|0|COCOA|1|"
      fontColor="#000000"
      lineColor="#000000"
      fillColor="#ccccff">
    <sourceConnections
        xsi:type="archimate:DiagramModelArchimateConnection"
        id="id-43644"
        font="1|Arial|10.0|0|COCOA|1|"
        fontColor="#000000"
        lineColor="#000000"
        source="id-43520"
        target="id-43512">
      <archimateRelationship
          xsi:type="archimate:InfluenceRelationship"
          href="InfluenceRelationship_id-47324.xml#id-47324"/>
    </sourceConnections>
    <bounds
        x="620"
        y="360"
        width="133"
        height="53"/>
    <archimateElement
        xsi:type="archimate:Goal"
        href="Goal_id-46565.xml#id-46565"/>
  </children>
  <children
      xsi:type="archimate:DiagramModelArchimateObject"
      id="id-43528"
      targetConnections="id-43649 id-43654 id-43704"
      font="1|Arial|10.0|0|COCOA|1|"
      fontColor="#000000"
      lineColor="#000000"
      fillColor="#ccccff">
    <bounds
        x="360"
        y="80"
        width="127"
        height="60"/>
    <archimateElement
        xsi:type="archimate:Driver"
        href="Driver_id-47250.xml#id-47250"/>
  </children>
  <children
      xsi:type="archimate:DiagramModelArchimateObject"
      id="id-43536"
      font="1|Arial|10.0|0|COCOA|1|"
      fontColor="#000000"
      lineColor="#000000"
      fillColor="#ccccff">
    <sourceConnections
        xsi:type="archimate:DiagramModelArchimateConnection"
        id="id-43649"
        font="1|Arial|10.0|0|COCOA|1|"
        fontColor="#000000"
        lineColor="#000000"
        source="id-43536"
        target="id-43528">
      <archimateRelationship
          xsi:type="archimate:AssociationRelationship"
          href="AssociationRelationship_id-47325.xml#id-47325"/>
    </sourceConnections>
    <bounds
        x="120"
        y="80"
        width="173"
        height="60"/>
    <archimateElement
        xsi:type="archimate:Assessment"
        href="Assessment_id-47244.xml#id-47244"/>
  </children>
  <children
      xsi:type="archimate:DiagramModelArchimateObject"
      id="id-43544"
      font="1|Arial|10.0|0|COCOA|1|"
      fontColor="#000000"
      lineColor="#000000"
      fillColor="#ccccff">
    <sourceConnections
        xsi:type="archimate:DiagramModelArchimateConnection"
        id="id-43654"
        font="1|Arial|10.0|0|COCOA|1|"
        fontColor="#000000"
        lineColor="#000000"
        source="id-43544"
        target="id-43528">
      <archimateRelationship
          xsi:type="archimate:AssociationRelationship"
          href="AssociationRelationship_id-47334.xml#id-47334"/>
    </sourceConnections>
    <bounds
        x="560"
        y="80"
        width="173"
        height="60"/>
    <archimateElement
        xsi:type="archimate:Assessment"
        href="Assessment_id-47245.xml#id-47245"/>
  </children>
  <children
      xsi:type="archimate:DiagramModelArchimateObject"
      id="id-43552"
      font="1|Arial|10.0|0|COCOA|1|"
      fontColor="#000000"
      lineColor="#000000"
      fillColor="#ccccff">
    <sourceConnections
        xsi:type="archimate:DiagramModelArchimateConnection"
        id="id-43659"
        font="1|Arial|10.0|0|COCOA|1|"
        fontColor="#000000"
        lineColor="#000000"
        source="id-43552"
        target="id-43576">
      <archimateRelationship
          xsi:type="archimate:AssociationRelationship"
          href="AssociationRelationship_id-47338.xml#id-47338"/>
    </sourceConnections>
    <bounds
        x="793"
        y="453"
        width="133"
        height="53"/>
    <archimateElement
        xsi:type="archimate:Assessment"
        href="Assessment_id-47255.xml#id-47255"/>
  </children>
  <children
      xsi:type="archimate:DiagramModelArchimateObject"
      id="id-43560"
      font="1|Arial|10.0|0|COCOA|1|"
      fontColor="#000000"
      lineColor="#000000"
      fillColor="#ccccff">
    <sourceConnections
        xsi:type="archimate:DiagramModelArchimateConnection"
        id="id-43664"
        font="1|Arial|10.0|0|COCOA|1|"
        fontColor="#000000"
        lineColor="#000000"
        source="id-43560"
        target="id-43496">
      <archimateRelationship
          xsi:type="archimate:AssociationRelationship"
          href="AssociationRelationship_id-47333.xml#id-47333"/>
    </sourceConnections>
    <bounds
        x="40"
        y="253"
        width="133"
        height="53"/>
    <archimateElement
        xsi:type="archimate:Assessment"
        href="Assessment_id-47246.xml#id-47246"/>
  </children>
  <children
      xsi:type="archimate:DiagramModelArchimateObject"
      id="id-43568"
      font="1|Arial|10.0|0|COCOA|1|"
      fontColor="#000000"
      lineColor="#000000"
      fillColor="#ccccff">
    <sourceConnections
        xsi:type="archimate:DiagramModelArchimateConnection"
        id="id-43669"
        font="1|Arial|10.0|0|COCOA|1|"
        fontColor="#000000"
        lineColor="#000000"
        source="id-43568"
        target="id-43520">
      <archimateRelationship
          xsi:type="archimate:AssociationRelationship"
          href="AssociationRelationship_id-47331.xml#id-47331"/>
    </sourceConnections>
    <bounds
        x="793"
        y="360"
        width="133"
        height="53"/>
    <archimateElement
        xsi:type="archimate:Assessment"
        href="Assessment_id-47256.xml#id-47256"/>
  </children>
  <children
      xsi:type="archimate:DiagramModelArchimateObject"
      id="id-43576"
      targetConnections="id-43659"
      font="1|Arial|10.0|0|COCOA|1|"
      fontColor="#000000"
      lineColor="#000000"
      fillColor="#ccccff">
    <sourceConnections
        xsi:type="archimate:DiagramModelArchimateConnection"
        id="id-43674"
        font="1|Arial|10.0|0|COCOA|1|"
        fontColor="#000000"
        lineColor="#000000"
        source="id-43576"
        target="id-43520">
      <archimateRelationship
          xsi:type="archimate:RealizationRelationship"
          href="RealizationRelationship_id-47326.xml#id-47326"/>
    </sourceConnections>
    <bounds
        x="620"
        y="453"
        width="133"
        height="53"/>
    <archimateElement
        xsi:type="archimate:Outcome"
        href="Outcome_id-46557.xml#id-46557"/>
  </children>
  <children
      xsi:type="archimate:DiagramModelArchimateObject"
      id="id-43584"
      targetConnections="id-43684"
      font="1|Arial|10.0|0|COCOA|1|"
      fontColor="#000000"
      lineColor="#000000"
      fillColor="#ccccff">
    <sourceConnections
        xsi:type="archimate:DiagramModelArchimateConnection"
        id="id-43679"
        font="1|Arial|10.0|0|COCOA|1|"
        fontColor="#000000"
        lineColor="#000000"
        source="id-43584"
        target="id-43512">
      <archimateRelationship
          xsi:type="archimate:InfluenceRelationship"
          href="InfluenceRelationship_id-47328.xml#id-47328"/>
    </sourceConnections>
    <bounds
        x="453"
        y="360"
        width="133"
        height="53"/>
    <archimateElement
        xsi:type="archimate:Goal"
        href="Goal_id-46574.xml#id-46574"/>
  </children>
  <children
      xsi:type="archimate:DiagramModelArchimateObject"
      id="id-43592"
      targetConnections="id-43689"
      font="1|Arial|10.0|0|COCOA|1|"
      fontColor="#000000"
      lineColor="#000000"
      fillColor="#ccccff">
    <sourceConnections
        xsi:type="archimate:DiagramModelArchimateConnection"
        id="id-43684"
        font="1|Arial|10.0|0|COCOA|1|"
        fontColor="#000000"
        lineColor="#000000"
        source="id-43592"
        target="id-43584">
      <archimateRelationship
          xsi:type="archimate:InfluenceRelationship"
          href="InfluenceRelationship_id-47335.xml#id-47335"/>
    </sourceConnections>
    <bounds
        x="453"
        y="453"
        width="133"
        height="53"/>
    <archimateElement
        xsi:type="archimate:Goal"
        href="Goal_id-46563.xml#id-46563"/>
  </children>
  <children
      xsi:type="archimate:DiagramModelArchimateObject"
      id="id-43600"
      font="1|Arial|10.0|0|COCOA|1|"
      fontColor="#000000"
      lineColor="#000000"
      fillColor="#ccccff">
    <sourceConnections
        xsi:type="archimate:DiagramModelArchimateConnection"
        id="id-43689"
        font="1|Arial|10.0|0|COCOA|1|"
        fontColor="#000000"
        lineColor="#000000"
        source="id-43600"
        target="id-43592">
      <archimateRelationship
          xsi:type="archimate:RealizationRelationship"
          href="RealizationRelationship_id-47332.xml#id-47332"/>
    </sourceConnections>
    <sourceConnections
        xsi:type="archimate:DiagramModelArchimateConnection"
        id="id-43694"
        font="1|Arial|10.0|0|COCOA|1|"
        fontColor="#000000"
        lineColor="#000000"
        source="id-43600"
        target="id-43608">
      <archimateRelationship
          xsi:type="archimate:InfluenceRelationship"
          href="InfluenceRelationship_id-47336.xml#id-47336"/>
    </sourceConnections>
    <bounds
        x="453"
        y="547"
        width="133"
        height="53"/>
    <archimateElement
        xsi:type="archimate:Outcome"
        href="Outcome_id-46336.xml#id-46336"/>
  </children>
  <children
      xsi:type="archimate:DiagramModelArchimateObject"
      id="id-43608"
      targetConnections="id-43694"
      font="1|Arial|10.0|0|COCOA|1|"
      fontColor="#000000"
      lineColor="#000000"
      fillColor="#ccccff">
    <sourceConnections
        xsi:type="archimate:DiagramModelArchimateConnection"
        id="id-43699"
        font="1|Arial|10.0|0|COCOA|1|"
        fontColor="#000000"
        lineColor="#000000"
        source="id-43608"
        target="id-43504">
      <archimateRelationship
          xsi:type="archimate:InfluenceRelationship"
          href="InfluenceRelationship_id-47329.xml#id-47329"/>
    </sourceConnections>
    <bounds
        x="297"
        y="453"
        width="133"
        height="53"/>
    <archimateElement
        xsi:type="archimate:Outcome"
        href="Outcome_id-46569.xml#id-46569"/>
  </children>
  <children
      xsi:type="archimate:DiagramModelArchimateObject"
      id="id-43616"
      targetConnections="id-43624 id-43639"
      font="1|Arial|10.0|0|COCOA|1|"
      fontColor="#000000"
      lineColor="#000000"
      fillColor="#ccccff">
    <sourceConnections
        xsi:type="archimate:DiagramModelArchimateConnection"
        id="id-43704"
        font="1|Arial|10.0|0|COCOA|1|"
        fontColor="#000000"
        lineColor="#000000"
        source="id-43616"
        target="id-43528">
      <archimateRelationship
          xsi:type="archimate:InfluenceRelationship"
          href="InfluenceRelationship_id-47340.xml#id-47340"/>
    </sourceConnections>
    <bounds
        x="357"
        y="173"
        width="133"
        height="53"/>
    <archimateElement
        xsi:type="archimate:Outcome"
        href="Outcome_id-47248.xml#id-47248"/>
  </children>
</archimate:ArchimateDiagramModel>
