<archimate:ArchimateDiagramModel
    xmlns:xsi="http://www.w3.org/2001/XMLSchema-instance"
    xmlns:archimate="http://www.archimatetool.com/archimate"
    name="Application Usage Diagram"
    id="id-37780"
    viewpoint="application_usage">
  <children
      xsi:type="archimate:DiagramModelArchimateObject"
      id="id-37783"
      font="1|Arial|10.0|0|COCOA|1|"
      fontColor="#000000"
      lineColor="#000000"
      fillColor="#ffffdd">
    <sourceConnections
        xsi:type="archimate:DiagramModelArchimateConnection"
        id="id-08b0cd244a35458b8af39b43867ef721"
        source="id-37783"
        target="id-37788">
      <archimateRelationship
          xsi:type="archimate:CompositionRelationship"
          href="CompositionRelationship_id-46640.xml#id-46640"/>
    </sourceConnections>
    <sourceConnections
        xsi:type="archimate:DiagramModelArchimateConnection"
        id="id-7defe5fe84ce4764b378fefbeb34d1c6"
        source="id-37783"
        target="id-37796">
      <archimateRelationship
          xsi:type="archimate:CompositionRelationship"
          href="CompositionRelationship_id-46642.xml#id-46642"/>
    </sourceConnections>
    <sourceConnections
        xsi:type="archimate:DiagramModelArchimateConnection"
        id="id-f127d267069f4eb3a92dced22239f1a5"
        source="id-37783"
        target="id-37804">
      <archimateRelationship
          xsi:type="archimate:CompositionRelationship"
          href="CompositionRelationship_id-46658.xml#id-46658"/>
    </sourceConnections>
    <sourceConnections
        xsi:type="archimate:DiagramModelArchimateConnection"
        id="id-761b30c0b66740b2a8daeda5784cb2fd"
        source="id-37783"
        target="id-37812">
      <archimateRelationship
          xsi:type="archimate:CompositionRelationship"
          href="CompositionRelationship_id-46633.xml#id-46633"/>
    </sourceConnections>
    <sourceConnections
        xsi:type="archimate:DiagramModelArchimateConnection"
        id="id-35738343b0d347d7956c66bc6d3a27c4"
        source="id-37783"
        target="id-37820">
      <archimateRelationship
          xsi:type="archimate:CompositionRelationship"
          href="CompositionRelationship_id-46626.xml#id-46626"/>
    </sourceConnections>
    <bounds
        x="107"
        y="127"
        width="680"
        height="93"/>
    <children
        xsi:type="archimate:DiagramModelArchimateObject"
        id="id-37788"
        targetConnections="id-37918 id-37923 id-08b0cd244a35458b8af39b43867ef721"
        font="1|Arial|10.0|0|COCOA|1|"
        fontColor="#000000"
        lineColor="#000000"
        fillColor="#ffffaf">
      <sourceConnections
          xsi:type="archimate:DiagramModelArchimateConnection"
          id="id-37898"
          font="1|Arial|10.0|0|COCOA|1|"
          fontColor="#000000"
          lineColor="#000000"
          source="id-37788"
          target="id-37796">
        <archimateRelationship
            xsi:type="archimate:TriggeringRelationship"
            href="TriggeringRelationship_id-46841.xml#id-46841"/>
      </sourceConnections>
      <bounds
          x="20"
          y="26"
          width="113"
          height="53"/>
      <archimateElement
          xsi:type="archimate:BusinessProcess"
          href="BusinessProcess_id-46641.xml#id-46641"/>
    </children>
    <children
        xsi:type="archimate:DiagramModelArchimateObject"
        id="id-37796"
        targetConnections="id-37898 id-37928 id-7defe5fe84ce4764b378fefbeb34d1c6"
        font="1|Arial|10.0|0|COCOA|1|"
        fontColor="#000000"
        lineColor="#000000"
        fillColor="#ffffaf">
      <sourceConnections
          xsi:type="archimate:DiagramModelArchimateConnection"
          id="id-37903"
          font="1|Arial|10.0|0|COCOA|1|"
          fontColor="#000000"
          lineColor="#000000"
          source="id-37796"
          target="id-37804">
        <archimateRelationship
            xsi:type="archimate:TriggeringRelationship"
            href="TriggeringRelationship_id-46839.xml#id-46839"/>
      </sourceConnections>
      <bounds
          x="153"
          y="26"
          width="140"
          height="53"/>
      <archimateElement
          xsi:type="archimate:BusinessProcess"
          href="BusinessProcess_id-46643.xml#id-46643"/>
    </children>
    <children
        xsi:type="archimate:DiagramModelArchimateObject"
        id="id-37804"
        targetConnections="id-37903 id-37933 id-37943 id-f127d267069f4eb3a92dced22239f1a5"
        font="1|Arial|10.0|0|COCOA|1|"
        fontColor="#000000"
        lineColor="#000000"
        fillColor="#ffffaf">
      <sourceConnections
          xsi:type="archimate:DiagramModelArchimateConnection"
          id="id-37908"
          font="1|Arial|10.0|0|COCOA|1|"
          fontColor="#000000"
          lineColor="#000000"
          source="id-37804"
          target="id-37820">
        <archimateRelationship
            xsi:type="archimate:TriggeringRelationship"
            href="TriggeringRelationship_id-46837.xml#id-46837"/>
      </sourceConnections>
      <bounds
          x="313"
          y="26"
          width="100"
          height="53"/>
      <archimateElement
          xsi:type="archimate:BusinessProcess"
          href="BusinessProcess_id-46659.xml#id-46659"/>
    </children>
    <children
        xsi:type="archimate:DiagramModelArchimateObject"
        id="id-37812"
        targetConnections="id-37913 id-37948 id-37953 id-761b30c0b66740b2a8daeda5784cb2fd"
        font="1|Arial|10.0|0|COCOA|1|"
        fontColor="#000000"
        lineColor="#000000"
        fillColor="#ffffaf">
      <bounds
          x="580"
          y="26"
          width="87"
          height="53"/>
      <archimateElement
          xsi:type="archimate:BusinessProcess"
          href="BusinessProcess_id-46294.xml#id-46294"/>
    </children>
    <children
        xsi:type="archimate:DiagramModelArchimateObject"
        id="id-37820"
        targetConnections="id-37908 id-37938 id-35738343b0d347d7956c66bc6d3a27c4"
        font="1|Arial|10.0|0|COCOA|1|"
        fontColor="#000000"
        lineColor="#000000"
        fillColor="#ffffaf">
      <sourceConnections
          xsi:type="archimate:DiagramModelArchimateConnection"
          id="id-37913"
          font="1|Arial|10.0|0|COCOA|1|"
          fontColor="#000000"
          lineColor="#000000"
          source="id-37820"
          target="id-37812">
        <archimateRelationship
            xsi:type="archimate:TriggeringRelationship"
            href="TriggeringRelationship_id-46836.xml#id-46836"/>
      </sourceConnections>
      <bounds
          x="440"
          y="26"
          width="113"
          height="53"/>
      <archimateElement
          xsi:type="archimate:BusinessProcess"
          href="BusinessProcess_id-46627.xml#id-46627"/>
    </children>
    <archimateElement
        xsi:type="archimate:BusinessProcess"
        href="BusinessProcess_id-46608.xml#id-46608"/>
  </children>
  <children
      xsi:type="archimate:DiagramModelArchimateObject"
      id="id-37831"
      targetConnections="id-37958"
      font="1|Arial|10.0|0|COCOA|1|"
      fontColor="#000000"
      lineColor="#000000"
      fillColor="#afffff">
    <sourceConnections
        xsi:type="archimate:DiagramModelArchimateConnection"
        id="id-37918"
        font="1|Arial|10.0|0|COCOA|1|"
        fontColor="#000000"
        lineColor="#000000"
        source="id-37831"
        target="id-37788">
      <archimateRelationship
          xsi:type="archimate:ServingRelationship"
          href="ServingRelationship_id-46982.xml#id-46982"/>
    </sourceConnections>
    <bounds
        x="73"
        y="260"
        width="80"
        height="40"/>
    <archimateElement
        xsi:type="archimate:ApplicationService"
        href="ApplicationService_id-46910.xml#id-46910"/>
  </children>
  <children
      xsi:type="archimate:DiagramModelArchimateObject"
      id="id-37838"
      targetConnections="id-37971"
      font="1|Arial|10.0|0|COCOA|1|"
      fontColor="#000000"
      lineColor="#000000"
      fillColor="#afffff">
    <sourceConnections
        xsi:type="archimate:DiagramModelArchimateConnection"
        id="id-37923"
        font="1|Arial|10.0|0|COCOA|1|"
        fontColor="#000000"
        lineColor="#000000"
        source="id-37838"
        target="id-37788">
      <archimateRelationship
          xsi:type="archimate:ServingRelationship"
          href="ServingRelationship_id-47009.xml#id-47009"/>
    </sourceConnections>
    <bounds
        x="213"
        y="260"
        width="100"
        height="40"/>
    <archimateElement
        xsi:type="archimate:ApplicationService"
        href="ApplicationService_id-46904.xml#id-46904"/>
  </children>
  <children
      xsi:type="archimate:DiagramModelArchimateObject"
      id="id-37845"
      targetConnections="id-37981"
      font="1|Arial|10.0|0|COCOA|1|"
      fontColor="#000000"
      lineColor="#000000"
      fillColor="#afffff">
    <sourceConnections
        xsi:type="archimate:DiagramModelArchimateConnection"
        id="id-37928"
        font="1|Arial|10.0|0|COCOA|1|"
        fontColor="#000000"
        lineColor="#000000"
        source="id-37845"
        target="id-37796">
      <archimateRelationship
          xsi:type="archimate:ServingRelationship"
          href="ServingRelationship_id-46986.xml#id-46986"/>
    </sourceConnections>
    <sourceConnections
        xsi:type="archimate:DiagramModelArchimateConnection"
        id="id-37933"
        font="1|Arial|10.0|0|COCOA|1|"
        fontColor="#000000"
        lineColor="#000000"
        source="id-37845"
        target="id-37804">
      <archimateRelationship
          xsi:type="archimate:ServingRelationship"
          href="ServingRelationship_id-46975.xml#id-46975"/>
    </sourceConnections>
    <sourceConnections
        xsi:type="archimate:DiagramModelArchimateConnection"
        id="id-37938"
        font="1|Arial|10.0|0|COCOA|1|"
        fontColor="#000000"
        lineColor="#000000"
        source="id-37845"
        target="id-37820">
      <archimateRelationship
          xsi:type="archimate:ServingRelationship"
          href="ServingRelationship_id-46934.xml#id-46934"/>
    </sourceConnections>
    <bounds
        x="393"
        y="260"
        width="100"
        height="40"/>
    <archimateElement
        xsi:type="archimate:ApplicationService"
        href="ApplicationService_id-46909.xml#id-46909"/>
  </children>
  <children
      xsi:type="archimate:DiagramModelArchimateObject"
      id="id-37852"
      targetConnections="id-37963"
      font="1|Arial|10.0|0|COCOA|1|"
      fontColor="#000000"
      lineColor="#000000"
      fillColor="#afffff">
    <sourceConnections
        xsi:type="archimate:DiagramModelArchimateConnection"
        id="id-37943"
        font="1|Arial|10.0|0|COCOA|1|"
        fontColor="#000000"
        lineColor="#000000"
        source="id-37852"
        target="id-37804">
      <archimateRelationship
          xsi:type="archimate:ServingRelationship"
          href="ServingRelationship_id-47002.xml#id-47002"/>
    </sourceConnections>
    <sourceConnections
        xsi:type="archimate:DiagramModelArchimateConnection"
        id="id-37948"
        font="1|Arial|10.0|0|COCOA|1|"
        fontColor="#000000"
        lineColor="#000000"
        source="id-37852"
        target="id-37812">
      <archimateRelationship
          xsi:type="archimate:ServingRelationship"
          href="ServingRelationship_id-46956.xml#id-46956"/>
    </sourceConnections>
    <bounds
        x="553"
        y="260"
        width="80"
        height="40"/>
    <archimateElement
        xsi:type="archimate:ApplicationService"
        href="ApplicationService_id-46907.xml#id-46907"/>
  </children>
  <children
      xsi:type="archimate:DiagramModelArchimateObject"
      id="id-37859"
      targetConnections="id-37976"
      font="1|Arial|10.0|0|COCOA|1|"
      fontColor="#000000"
      lineColor="#000000"
      fillColor="#afffff">
    <sourceConnections
        xsi:type="archimate:DiagramModelArchimateConnection"
        id="id-37953"
        font="1|Arial|10.0|0|COCOA|1|"
        fontColor="#000000"
        lineColor="#000000"
        source="id-37859"
        target="id-37812">
      <archimateRelationship
          xsi:type="archimate:ServingRelationship"
          href="ServingRelationship_id-46963.xml#id-46963"/>
    </sourceConnections>
    <bounds
        x="693"
        y="260"
        width="80"
        height="40"/>
    <archimateElement
        xsi:type="archimate:ApplicationService"
        href="ApplicationService_id-46906.xml#id-46906"/>
  </children>
  <children
      xsi:type="archimate:DiagramModelArchimateObject"
      id="id-37866"
      font="1|Arial|10.0|0|COCOA|1|"
      fontColor="#000000"
      lineColor="#000000"
      fillColor="#afffff">
    <sourceConnections
        xsi:type="archimate:DiagramModelArchimateConnection"
        id="id-37958"
        font="1|Arial|10.0|0|COCOA|1|"
        fontColor="#000000"
        lineColor="#000000"
        source="id-37866"
        target="id-37831">
      <archimateRelationship
          xsi:type="archimate:RealizationRelationship"
          href="RealizationRelationship_id-46996.xml#id-46996"/>
    </sourceConnections>
    <sourceConnections
        xsi:type="archimate:DiagramModelArchimateConnection"
        id="id-37963"
        font="1|Arial|10.0|0|COCOA|1|"
        fontColor="#000000"
        lineColor="#000000"
        source="id-37866"
        target="id-37852">
      <bendpoints
          startX="34"
          startY="-40"
          endX="-446"
          endY="53"/>
      <bendpoints
          startX="480"
          startY="-40"
          endY="53"/>
      <archimateRelationship
          xsi:type="archimate:RealizationRelationship"
          href="RealizationRelationship_id-47003.xml#id-47003"/>
    </sourceConnections>
    <bounds
        x="60"
        y="347"
        width="107"
        height="53"/>
    <archimateElement
        xsi:type="archimate:ApplicationComponent"
        href="ApplicationComponent_id-46860.xml#id-46860"/>
  </children>
  <children
      xsi:type="archimate:DiagramModelArchimateObject"
      id="id-37874"
      font="1|Arial|10.0|0|COCOA|1|"
      fontColor="#000000"
      lineColor="#000000"
      fillColor="#afffff">
    <sourceConnections
        xsi:type="archimate:DiagramModelArchimateConnection"
        id="id-37971"
        font="1|Arial|10.0|0|COCOA|1|"
        fontColor="#000000"
        lineColor="#000000"
        source="id-37874"
        target="id-37838">
      <archimateRelationship
          xsi:type="archimate:RealizationRelationship"
          href="RealizationRelationship_id-46949.xml#id-46949"/>
    </sourceConnections>
    <bounds
        x="203"
        y="347"
        width="120"
        height="53"/>
    <archimateElement
        xsi:type="archimate:ApplicationComponent"
        href="ApplicationComponent_id-46862.xml#id-46862"/>
  </children>
  <children
      xsi:type="archimate:DiagramModelArchimateObject"
      id="id-37882"
      font="1|Arial|10.0|0|COCOA|1|"
      fontColor="#000000"
      lineColor="#000000"
      fillColor="#afffff">
    <sourceConnections
        xsi:type="archimate:DiagramModelArchimateConnection"
        id="id-37976"
        font="1|Arial|10.0|0|COCOA|1|"
        fontColor="#000000"
        lineColor="#000000"
        source="id-37882"
        target="id-37859">
      <archimateRelationship
          xsi:type="archimate:RealizationRelationship"
          href="RealizationRelationship_id-46998.xml#id-46998"/>
    </sourceConnections>
    <bounds
        x="667"
        y="347"
        width="133"
        height="53"/>
    <archimateElement
        xsi:type="archimate:ApplicationComponent"
        href="ApplicationComponent_id-46915.xml#id-46915"/>
  </children>
  <children
      xsi:type="archimate:DiagramModelArchimateObject"
      id="id-37890"
      font="1|Arial|10.0|0|COCOA|1|"
      fontColor="#000000"
      lineColor="#000000"
      fillColor="#afffff">
    <sourceConnections
        xsi:type="archimate:DiagramModelArchimateConnection"
        id="id-37981"
        font="1|Arial|10.0|0|COCOA|1|"
        fontColor="#000000"
        lineColor="#000000"
        source="id-37890"
        target="id-37845">
      <archimateRelationship
          xsi:type="archimate:RealizationRelationship"
          href="RealizationRelationship_id-46995.xml#id-46995"/>
    </sourceConnections>
    <bounds
        x="377"
        y="347"
        width="133"
        height="53"/>
    <archimateElement
        xsi:type="archimate:ApplicationComponent"
        href="ApplicationComponent_id-46918.xml#id-46918"/>
  </children>
</archimate:ArchimateDiagramModel>
